tape/__init__.py
tape/_version.py
tape/ensemble.py
tape/ensemble_frame.py
tape/ensemble_readers.py
tape/timeseries.py
tape/analysis/__init__.py
tape/analysis/base.py
tape/analysis/feature_extractor.py
tape/analysis/light_curve.py
tape/analysis/stetsonj.py
tape/analysis/structurefunction2.py
tape/analysis/structure_function/__init__.py
tape/analysis/structure_function/base_argument_container.py
tape/analysis/structure_function/base_calculator.py
tape/analysis/structure_function/calculator_registrar.py
tape/analysis/structure_function/sf_light_curve.py
tape/analysis/structure_function/basic/__init__.py
tape/analysis/structure_function/basic/calculator.py
tape/analysis/structure_function/bauer_2009a/__init__.py
tape/analysis/structure_function/bauer_2009a/calculator.py
tape/analysis/structure_function/bauer_2009b/__init__.py
tape/analysis/structure_function/bauer_2009b/calculator.py
tape/analysis/structure_function/macleod_2012/__init__.py
tape/analysis/structure_function/macleod_2012/calculator.py
tape/analysis/structure_function/schmidt_2010/__init__.py
tape/analysis/structure_function/schmidt_2010/calculator.py
tape/utils/__init__.py
tape/utils/utils.py
tape/utils/column_mapper/__init__.py
tape/utils/column_mapper/column_mapper.py
lf_tape-0.4.1.dist-info/LICENSE
lf_tape-0.4.1.dist-info/METADATA
lf_tape-0.4.1.dist-info/WHEEL
lf_tape-0.4.1.dist-info/top_level.txt
lf_tape-0.4.1.dist-info/RECORD
