Metadata-Version: 2.1
Name: lf-tape
Version: 0.4.1
Author-email: LINCC Frameworks Team <Lincc-frameworks-team@lists.lsst.org>
License: MIT License
Project-URL: Source code, https://github.com/lincc-frameworks/tape
Project-URL: Documentation, https://tape.readthedocs.io/
Classifier: Development Status :: 4 - Beta
Classifier: License :: OSI Approved :: MIT License
Classifier: Intended Audience :: Developers
Classifier: Intended Audience :: Science/Research
Classifier: Operating System :: OS Independent
Classifier: Programming Language :: Python
Requires-Python: >=3.9
License-File: LICENSE
Requires-Dist: pandas
Requires-Dist: numpy
Requires-Dist: dask >=2024.3.0
Requires-Dist: dask-expr <1.0.11
Requires-Dist: dask[distributed] >=2024.3.0
Requires-Dist: pyarrow
Requires-Dist: pyvo
Requires-Dist: scipy
Requires-Dist: requests
Requires-Dist: aiohttp
Requires-Dist: coverage
Requires-Dist: deprecated
Requires-Dist: light-curve <0.10.0,>=0.9.0
Requires-Dist: lsdb
Provides-Extra: dev
Requires-Dist: asv ==0.6.3 ; extra == 'dev'
Requires-Dist: black ; extra == 'dev'
Requires-Dist: jupyter ; extra == 'dev'
Requires-Dist: pre-commit ; extra == 'dev'
Requires-Dist: pytest ; extra == 'dev'
Requires-Dist: pytest-cov ; extra == 'dev'
